SQLAlchemy_DB_ORM_Template/App.py
SQLAlchemy_DB_ORM_Template/Manage.py
SQLAlchemy_DB_ORM_Template/__init__.py
SQLAlchemy_DB_ORM_Template/BlueWhale/AppStart/AppStart.py
SQLAlchemy_DB_ORM_Template/BlueWhale/Initializer/Initializer.py
SQLAlchemy_DB_ORM_Template/BlueWhale/MigrationFolderOS/MigrationFolderOS.py
SQLAlchemy_DB_ORM_Template/Entity/DbConfig/DbConfig.py
SQLAlchemy_DB_ORM_Template/Entity/ModelBase/ModelBase.py
SQLAlchemy_DB_ORM_Template/Entity/Packages/EntityModels.py
SQLAlchemy_DB_ORM_Template/Entity/Table/AuthenticationLogs.py
SQLAlchemy_DB_ORM_Template/Entity/Table/Authentications.py
SQLAlchemy_DB_ORM_Template/Entity/Table/Users.py
SQLAlchemy_DB_ORM_Template/Utils/GeneralLists.py
SQLAlchemy_DB_ORM_Template-1.1.0.dist-info/LICENSE
SQLAlchemy_DB_ORM_Template-1.1.0.dist-info/METADATA
SQLAlchemy_DB_ORM_Template-1.1.0.dist-info/WHEEL
SQLAlchemy_DB_ORM_Template-1.1.0.dist-info/top_level.txt
SQLAlchemy_DB_ORM_Template-1.1.0.dist-info/RECORD
